src/LaPosteAPI/LaPoste.py
src/LaPosteAPI/LaPosteExeptions.py
src/LaPosteAPI/__init__.py
laposte-0.1.1.dist-info/METADATA
laposte-0.1.1.dist-info/WHEEL
laposte-0.1.1.dist-info/licenses/LICENSE
laposte-0.1.1.dist-info/RECORD
