Metadata-Version: 2.1
Name: laposte
Version: 0.1.1
Summary: La Poste API in Python
Project-URL: Homepage, https://lapostepython.readthedocs.io/fr/latest/
Project-URL: Bug Tracker, https://github.com/444ldx/la_poste_python/issues
Project-URL: Code, https://github.com/444ldx/la_poste_python
Author-email: ldx <fr.ldxdev@gmail.com>
License-File: LICENSE
Classifier: License :: OSI Approved :: MIT License
Classifier: Operating System :: OS Independent
Classifier: Programming Language :: Python :: 3
Requires-Python: >=3.7
Requires-Dist: requests
